xshl/session/__about__.py
xshl/session/__init__.py
xshl/session/claims.py
xshl/session/keys.py
xshl_session-0.0.1.data/data/COPYRIGHT
xshl_session-0.0.1.data/data/LICENSE
xshl_session-0.0.1.dist-info/licenses/LICENSE
xshl_session-0.0.1.dist-info/METADATA
xshl_session-0.0.1.dist-info/WHEEL
xshl_session-0.0.1.dist-info/top_level.txt
xshl_session-0.0.1.dist-info/RECORD
