Metadata-Version: 2.4
Name: xshl-session
Version: 0.0.1
Summary: Python Library for XSHL Session
Home-page: https://github.com/mcode-cc/py-xshl-session
Author: MCode GmbH
Author-email: python@xshl.org
License: GPLv3
Project-URL: Bug Tracker, https://github.com/mcode-cc/py-xshl-session/issues
Project-URL: Source Code, https://github.com/mcode-cc/py-xshl-session
Keywords: Session in JWT
Platform: Any
Classifier: License :: OSI Approved :: GNU General Public License v3 (GPLv3)
Classifier: Development Status :: 1 - Planning
Classifier: Environment :: No Input/Output (Daemon)
Classifier: Environment :: Console
Classifier: Intended Audience :: Developers
Classifier: Operating System :: OS Independent
Classifier: Programming Language :: Python :: 3.8
Classifier: Programming Language :: Python :: 3.9
Classifier: Programming Language :: Python :: 3 :: Only
Classifier: Programming Language :: Python :: Implementation :: CPython
Classifier: Programming Language :: Python :: Implementation :: PyPy
Classifier: Topic :: Internet
Classifier: Topic :: Communications
Classifier: Topic :: Database
Classifier: Topic :: Software Development :: Libraries
Classifier: Topic :: Software Development :: Libraries :: Python Modules
Classifier: Topic :: Software Development :: Libraries :: Application Frameworks
Classifier: Topic :: System :: Networking
Requires-Python: >=3.8
License-File: LICENSE
Requires-Dist: xshl-target>=0.3.2
Requires-Dist: authlib>=1.3.0
Requires-Dist: requests>=2.32.4
Requires-Dist: aiohttp>=3.12.15
Dynamic: author
Dynamic: author-email
Dynamic: classifier
Dynamic: description
Dynamic: description-content-type
Dynamic: home-page
Dynamic: keywords
Dynamic: license
Dynamic: license-file
Dynamic: platform
Dynamic: project-url
Dynamic: requires-dist
Dynamic: requires-python
Dynamic: summary
